README
authgoogle_middleware.py
setup.py
authgoogle_middleware.egg-info/PKG-INFO
authgoogle_middleware.egg-info/SOURCES.txt
authgoogle_middleware.egg-info/dependency_links.txt
authgoogle_middleware.egg-info/requires.txt
authgoogle_middleware.egg-info/top_level.txt