Metadata-Version: 1.1
Name: authgoogle-middleware
Version: 0.2.1
Summary: Google authentication middleware
Home-page: https://bitbucket.org/uptimebox/authgoogle-middleware
Author: Mikhail Lukyanchenko
Author-email: ml@uptimebox.ru
License: BSD License
Platform: UNKNOWN
Classifier: Development Status :: 4 - Beta
Classifier: Environment :: Web Environment
Classifier: Intended Audience :: Developers
Classifier: License :: OSI Approved :: BSD License
Classifier: Programming Language :: Python
Classifier: Topic :: Internet :: WWW/HTTP :: WSGI :: Middleware
